apscheduler_di/__init__.py
apscheduler_di/_binding.py
apscheduler_di/_events.py
apscheduler_di/_helper.py
apscheduler_di/_inject.py
apscheduler_di/_serialization.py
apscheduler_di/decorator.py
apscheduler_di-0.0.7.dist-info/WHEEL
apscheduler_di-0.0.7.dist-info/METADATA
apscheduler_di-0.0.7.dist-info/RECORD
